{"nodes": [{"id": "e_workspace_\u4ee3\u7801_spring_ai_spring_ai_model_src_main_java_org_springframework_ai_model_model_java", "label": "Model.java", "file_type": "code", "source_file": "E:\\workSpace\\\u4ee3\u7801\\spring-ai\\spring-ai-model\\src\\main\\java\\org\\springframework\\ai\\model\\Model.java", "source_location": "L1"}, {"id": "model_model_model", "label": "Model", "file_type": "code", "source_file": "E:\\workSpace\\\u4ee3\u7801\\spring-ai\\spring-ai-model\\src\\main\\java\\org\\springframework\\ai\\model\\Model.java", "source_location": "L31"}, {"id": "model_model_model_call", "label": ".call()", "file_type": "code", "source_file": "E:\\workSpace\\\u4ee3\u7801\\spring-ai\\spring-ai-model\\src\\main\\java\\org\\springframework\\ai\\model\\Model.java", "source_location": "L38"}], "edges": [{"source": "e_workspace_\u4ee3\u7801_spring_ai_spring_ai_model_src_main_java_org_springframework_ai_model_model_java", "target": "model_model_model", "relation": "contains", "confidence": "EXTRACTED", "source_file": "E:\\workSpace\\\u4ee3\u7801\\spring-ai\\spring-ai-model\\src\\main\\java\\org\\springframework\\ai\\model\\Model.java", "source_location": "L31", "weight": 1.0}, {"source": "model_model_model", "target": "model_model_model_call", "relation": "method", "confidence": "EXTRACTED", "source_file": "E:\\workSpace\\\u4ee3\u7801\\spring-ai\\spring-ai-model\\src\\main\\java\\org\\springframework\\ai\\model\\Model.java", "source_location": "L38", "weight": 1.0}], "raw_calls": []}